{
  "schemaVersion": "1.0.0",
  "projectStateVersion": 3,
  "summary": "New project",
  "architectural_notes": [],
  "known_issues": [],
  "isFixRequest": false,
  "existing_features": [
    {
      "id": "feature-fix-the-expected-v3-response-body-candid-interface-mismatch-error-that-occurs-when-a-user-attempts-to-create-a-blog-post-so-that-blog-post-creation-completes-successfully-without-errors",
      "title": "Fix the 'Expected v3 response body' Candid interface mismatch error that occurs when a user attempts to create a blog post, so that blog post creation completes successfully without errors.",
      "reqIds": [
        "REQ-1"
      ],
      "version": 1
    }
  ],
  "new_feature_requests": [],
  "projectName": "Retry failed deployment build",
  "clarification_mode": "instant",
  "clarification_rounds": 0
}